jupyterlab_pyflyby/__init__.py
jupyterlab_pyflyby/_version.py
jupyterlab_pyflyby/handlers.py
jupyterlab_pyflyby-5.1.3.data/data/etc/jupyter/jupyter_notebook_config.d/jupyterlab_pyflyby.json
jupyterlab_pyflyby-5.1.3.data/data/etc/jupyter/jupyter_server_config.d/jupyterlab_pyflyby.json
jupyterlab_pyflyby-5.1.3.data/data/share/jupyter/labextensions/@deshaw/jupyterlab-pyflyby/package.json
jupyterlab_pyflyby-5.1.3.data/data/share/jupyter/labextensions/@deshaw/jupyterlab-pyflyby/schemas/@deshaw/jupyterlab-pyflyby/package.json.orig
jupyterlab_pyflyby-5.1.3.data/data/share/jupyter/labextensions/@deshaw/jupyterlab-pyflyby/schemas/@deshaw/jupyterlab-pyflyby/plugin.json
jupyterlab_pyflyby-5.1.3.data/data/share/jupyter/labextensions/@deshaw/jupyterlab-pyflyby/static/16.c1180c19202ec748a72d.js
jupyterlab_pyflyby-5.1.3.data/data/share/jupyter/labextensions/@deshaw/jupyterlab-pyflyby/static/448.0871692736f84e41b8bd.js
jupyterlab_pyflyby-5.1.3.data/data/share/jupyter/labextensions/@deshaw/jupyterlab-pyflyby/static/736.09b82b0ba4aaa6b24062.js
jupyterlab_pyflyby-5.1.3.data/data/share/jupyter/labextensions/@deshaw/jupyterlab-pyflyby/static/remoteEntry.d7037c7eee8f4498b055.js
jupyterlab_pyflyby-5.1.3.data/data/share/jupyter/labextensions/@deshaw/jupyterlab-pyflyby/static/style.js
jupyterlab_pyflyby-5.1.3.data/data/share/jupyter/labextensions/@deshaw/jupyterlab-pyflyby/static/third-party-licenses.json
jupyterlab_pyflyby-5.1.3.data/data/share/jupyter/labextensions/@deshaw/jupyterlab-pyflyby/install.json
jupyterlab_pyflyby-5.1.3.dist-info/METADATA
jupyterlab_pyflyby-5.1.3.dist-info/WHEEL
jupyterlab_pyflyby-5.1.3.dist-info/licenses/LICENSE.txt
jupyterlab_pyflyby-5.1.3.dist-info/RECORD
